magnum_tempest_plugin/__init__.py
magnum_tempest_plugin/config.py
magnum_tempest_plugin/plugin.py
magnum_tempest_plugin/common/__init__.py
magnum_tempest_plugin/common/base.py
magnum_tempest_plugin/common/client.py
magnum_tempest_plugin/common/config.py
magnum_tempest_plugin/common/datagen.py
magnum_tempest_plugin/common/manager.py
magnum_tempest_plugin/common/models.py
magnum_tempest_plugin/common/utils.py
magnum_tempest_plugin/common/templates/__init__.py
magnum_tempest_plugin/common/templates/cluster.py
magnum_tempest_plugin/common/templates/cluster_template.py
magnum_tempest_plugin/common/templates/cluster_template_admin.py
magnum_tempest_plugin/tests/__init__.py
magnum_tempest_plugin/tests/api/__init__.py
magnum_tempest_plugin/tests/api/base.py
magnum_tempest_plugin/tests/api/v1/__init__.py
magnum_tempest_plugin/tests/api/v1/test_cluster.py
magnum_tempest_plugin/tests/api/v1/test_cluster_template.py
magnum_tempest_plugin/tests/api/v1/test_cluster_template_admin.py
magnum_tempest_plugin/tests/api/v1/test_magnum_service.py
magnum_tempest_plugin/tests/api/v1/clients/__init__.py
magnum_tempest_plugin/tests/api/v1/clients/cert_client.py
magnum_tempest_plugin/tests/api/v1/clients/cluster_client.py
magnum_tempest_plugin/tests/api/v1/clients/cluster_template_client.py
magnum_tempest_plugin/tests/api/v1/clients/magnum_service_client.py
magnum_tempest_plugin/tests/api/v1/models/__init__.py
magnum_tempest_plugin/tests/api/v1/models/cert_model.py
magnum_tempest_plugin/tests/api/v1/models/cluster_id_model.py
magnum_tempest_plugin/tests/api/v1/models/cluster_model.py
magnum_tempest_plugin/tests/api/v1/models/cluster_template_model.py
magnum_tempest_plugin/tests/api/v1/models/cluster_templatepatch_model.py
magnum_tempest_plugin/tests/api/v1/models/clusterpatch_model.py
magnum_tempest_plugin/tests/api/v1/models/magnum_service_model.py
magnum_tempest_plugin/tests/api/v1/rbac/__init__.py
magnum_tempest_plugin/tests/api/v1/rbac/base.py
magnum_tempest_plugin-2.9.0.dist-info/AUTHORS
magnum_tempest_plugin-2.9.0.dist-info/LICENSE
magnum_tempest_plugin-2.9.0.dist-info/METADATA
magnum_tempest_plugin-2.9.0.dist-info/WHEEL
magnum_tempest_plugin-2.9.0.dist-info/entry_points.txt
magnum_tempest_plugin-2.9.0.dist-info/pbr.json
magnum_tempest_plugin-2.9.0.dist-info/top_level.txt
magnum_tempest_plugin-2.9.0.dist-info/RECORD
