Metadata-Version: 2.1
Name: magnum_tempest_plugin
Version: 2.9.0
Summary: Tempest plugin for Magnum Project
Home-page: https://opendev.org/openstack/magnum-tempest-plugin
Author: OpenStack
Author-email: openstack-discuss@lists.openstack.org
Classifier: Environment :: OpenStack
Classifier: Intended Audience :: Information Technology
Classifier: Intended Audience :: System Administrators
Classifier: License :: OSI Approved :: Apache Software License
Classifier: Operating System :: POSIX :: Linux
Classifier: Programming Language :: Python
Classifier: Programming Language :: Python :: 3
Classifier: Programming Language :: Python :: 3.8
Classifier: Programming Language :: Python :: 3.9
Classifier: Programming Language :: Python :: 3.10
Classifier: Programming Language :: Python :: 3.11
Classifier: Programming Language :: Python :: 3.12
License-File: LICENSE
License-File: AUTHORS
Requires-Dist: pbr !=2.1.0,>=2.0.0
Requires-Dist: tempest >=17.1.0
Requires-Dist: oslo.config >=5.2.0
Requires-Dist: oslo.log >=3.36.0
Requires-Dist: kubernetes >=26.0.0
